package/__init__.py
package/pyrecommend.py
package/recopy.py
recopy-0.1.1.dist-info/METADATA
recopy-0.1.1.dist-info/WHEEL
recopy-0.1.1.dist-info/top_level.txt
recopy-0.1.1.dist-info/RECORD
