Metadata-Version: 2.1
Name: recopy
Version: 0.1.1
Summary: A library to do recommendations based on matrix
Home-page: https://github.com/blacker-sd/pyrecommendation
Author: Ziqian Wang
Author-email: 1793982387@qq.com
License: UNKNOWN
Platform: UNKNOWN
Classifier: Programming Language :: Python :: 3
Classifier: Operating System :: OS Independent
Classifier: Development Status :: 3 - Alpha
Requires-Python: >=3.6
Requires-Dist: numpy
Requires-Dist: pandas
Requires-Dist: scikit-learn
